netbox_plugin_osism/__init__.py
netbox_plugin_osism/template_content.py
netbox_plugin_osism/version.py
netbox_plugin_osism/templates/netbox_plugin_osism/interfaces.html
netbox_plugin_osism-0.0.1.dist-info/LICENSE
netbox_plugin_osism-0.0.1.dist-info/METADATA
netbox_plugin_osism-0.0.1.dist-info/WHEEL
netbox_plugin_osism-0.0.1.dist-info/top_level.txt
netbox_plugin_osism-0.0.1.dist-info/RECORD
